CHANGELOG.rst
blackcellmagic.py
blackcellmagic-0.0.3.dist-info/LICENSE
blackcellmagic-0.0.3.dist-info/WHEEL
blackcellmagic-0.0.3.dist-info/METADATA
blackcellmagic-0.0.3.dist-info/RECORD
