Metadata-Version: 2.1
Name: blackcellmagic
Version: 0.0.3
Summary: IPython magic command to format python code in cell using black.
Home-page: https://github.com/csurfer/blackcellmagic
License: MIT
Keywords: automation,formatter,yapf,autopep8,pyfmt,gofmt,rustfmt,IPython,black,jupyter
Author: csurfer
Author-email: sharma.vishwas88@gmail.com
Requires-Python: >=3.6.2,<4.0.0
Classifier: Development Status :: 3 - Alpha
Classifier: Environment :: Console
Classifier: Intended Audience :: Developers
Classifier: License :: OSI Approved :: MIT License
Classifier: Operating System :: OS Independent
Classifier: Programming Language :: Python
Classifier: Programming Language :: Python :: 3
Classifier: Programming Language :: Python :: 3 :: Only
Classifier: Programming Language :: Python :: 3.6
Classifier: Programming Language :: Python :: 3.7
Classifier: Programming Language :: Python :: 3.8
Classifier: Programming Language :: Python :: 3.9
Classifier: Topic :: Software Development :: Libraries :: Python Modules
Classifier: Topic :: Software Development :: Quality Assurance
Requires-Dist: black (>=21.9b0,<22.0)
Requires-Dist: jupyter (>=1.0.0,<2.0.0)
Project-URL: Repository, https://github.com/csurfer/blackcellmagic
